commongroups/__init__.py
commongroups/_about.py
commongroups/cmgroup.py
commongroups/env.py
commongroups/errors.py
commongroups/googlesheet.py
commongroups/hypertext.py
commongroups/logconf.py
commongroups/ops.py
commongroups/query.py
commongroups/run.py
commongroups/templates/cmgroup.html
commongroups/templates/common.css
commongroups/templates/directory.html
commongroups/tests/__init__.py
commongroups/tests/params.json
commongroups/tests/test_commongroups.py
commongroups-2017.4.4.dist-info/DESCRIPTION.rst
commongroups-2017.4.4.dist-info/METADATA
commongroups-2017.4.4.dist-info/RECORD
commongroups-2017.4.4.dist-info/WHEEL
commongroups-2017.4.4.dist-info/entry_points.txt
commongroups-2017.4.4.dist-info/metadata.json
commongroups-2017.4.4.dist-info/top_level.txt
commongroups-2017.4.4.dist-info/zip-safe
