Metadata-Version: 2.0
Name: commongroups
Version: 2017.4.4
Summary: Molecular structure-based classification of chemicals in known hazard groups
Home-page: https://github.com/akokai/commongroups
Author: Akos Kokai, Michel Dedeo, and Fred Cauthen
Author-email: akokai@berkeley.edu
License: MIT
Keywords: science chemistry toxicology
Platform: UNKNOWN
Classifier: Development Status :: 3 - Alpha
Classifier: License :: OSI Approved :: MIT License
Classifier: Intended Audience :: Science/Research
Classifier: Programming Language :: Python :: 3
Classifier: Programming Language :: Python :: 3.5
Classifier: Topic :: Database
Classifier: Topic :: Scientific/Engineering :: Chemistry
Requires-Dist: ashes
Requires-Dist: boltons
Requires-Dist: gspread
Requires-Dist: oauth2client
Requires-Dist: pandas
Requires-Dist: psycopg2
Requires-Dist: sqlalchemy
Requires-Dist: xlrd
Requires-Dist: xlsxwriter
